Metadata-Version: 2.1
Name: tinytcp
Version: 1.0.0
Summary: Event based package for tcp server/client on top of python sockets package
Home-page: https://github.com/M-Boukhlouf/tinytcp
Author: Mohammed Boukhlouf
Author-email: mohammed.boukhlouf@outlook.com
License: UNKNOWN
Platform: UNKNOWN
Classifier: Programming Language :: Python :: 3
Classifier: License :: OSI Approved :: MIT License
Classifier: Operating System :: OS Independent
Requires-Python: >=3.6
